__init__.py
sharepointing.py
sharepointing-0.2.2.dist-info/LICENSE
sharepointing-0.2.2.dist-info/METADATA
sharepointing-0.2.2.dist-info/WHEEL
sharepointing-0.2.2.dist-info/top_level.txt
sharepointing-0.2.2.dist-info/RECORD
