Metadata-Version: 2.1
Name: sharepointing
Version: 0.2.2
Summary: A package to establish a connection to SharePoint site, and upload files through that connection
Home-page: https://github.com/mo-sijar/sharepointing
Author: Mo Sijarrey
Author-email: Mo Sijarrey <mo.sijar@gmail.com>
Project-URL: Homepage, https://github.com/mo-sijar
Classifier: Programming Language :: Python :: 3
Classifier: Operating System :: OS Independent
Requires-Python: >=3.10
License-File: LICENSE
Requires-Dist: Office365-REST-Python-Client (>=2.3.16)
